mse_antede_fs2020_utilities/__init__.py
mse_antede_fs2020_utilities/preprocessing.py
mse_antede_fs2020_utilities-0.3.dist-info/METADATA
mse_antede_fs2020_utilities-0.3.dist-info/WHEEL
mse_antede_fs2020_utilities-0.3.dist-info/top_level.txt
mse_antede_fs2020_utilities-0.3.dist-info/RECORD
