Metadata-Version: 2.1
Name: mse-antede-fs2020-utilities
Version: 0.3
Summary: Utilities for AnTeDe course.
Home-page: http://github.com/markif/mse_antede_fs2020_utilities
Author: Fabian
License: MIT
Platform: UNKNOWN
Requires-Dist: nltk
Requires-Dist: numpy
Requires-Dist: pandas
Requires-Dist: contractions
Requires-Dist: inflect
Requires-Dist: beautifulsoup4
